README.rst
setup.py
mpa/__init__.py
mpa/mpa.py
mpa/mpa_core.py
mpa/mpa_core_io.py
mpa/mpa_core_parameter.py
mpa/mpa_core_plot.py
mpa/mpa_data_type_ConfigRecordParser.py
mpa/mpa_data_type_InfoCollector.py
mpa/mpa_modifier_axis.py
mpa/mpa_modifier_color_bar.py
mpa/mpa_modifier_data.py
mpa/mpa_modifier_figure.py
mpa/mpa_modifier_legend.py
mpa/mpa_modifier_panel.py
mpa/mpa_parameter_axis.py
mpa/mpa_parameter_color.py
mpa/mpa_parameter_color_bar.py
mpa/mpa_parameter_data.py
mpa/mpa_parameter_dependency.py
mpa/mpa_parameter_figure.py
mpa/mpa_parameter_grid.py
mpa/mpa_parameter_legend.py
mpa/mpa_parameter_panel.py
mpa/mpa_parameter_tick.py
mpa/mpa_parameter_twin_axis.py
mpa/mpa_plot_controller.py
mpa/mpa_plot_create.py
mpa/mpa_plot_figure.py
mpa/mpa_plot_histogram.py
mpa/mpa_plot_line.py
mpa/mpa_plot_matrix.py
mpa/mpa_plot_panel.py
mpa/mpa_proxy_modifier_axis.py
mpa/mpa_proxy_modifier_color_bar.py
mpa/mpa_proxy_modifier_figure.py
mpa/mpa_proxy_modifier_legend.py
mpa/mpa_proxy_modifier_panel.py
mpa/mpa_reader_data_parameter.py
mpa/mpa_reader_global_parameter.py
mpa/mpa_reader_local_parameter.py
mpa/mpa_syntax_marker.py
mpa/mpa_toolkit.py
mpa/mpa_writer_figure.py
mpa.egg-info/PKG-INFO
mpa.egg-info/SOURCES.txt
mpa.egg-info/dependency_links.txt
mpa.egg-info/top_level.txt