Metadata-Version: 1.0
Name: mpa
Version: 0.1.1b6
Summary: Matplotlib Plotting Assistant
Home-page: https://github.com/yuhangwang/MPA
Author: Yuhang Wang
Author-email: UNKNOWN
License: BSD 3-Clause License
Platform: UNKNOWN
